lerc_control/README.md
lerc_control/__init__.py
lerc_control/collect.py
lerc_control/deploy_lerc.py
lerc_control/helpers.py
lerc_control/remediate.py
lerc_control/scripted.py
lerc_control/upgrade_clients.py
lerc_control/bin/deploy_lerc
lerc_control/bin/lerc_ui
lerc_control/etc/dev_lerc.ini
lerc_control/etc/example_collect_routine.ini
lerc_control/etc/example_lerc.ini
lerc_control/etc/example_remediate_routine.ini
lerc_control/etc/lerc.ini
lerc_control/lerc_api/__init__.py
lerc_control/scripts/collect_autoruns.ini
lerc_control/scripts/collect_browsing_history.ini
lerc_control/scripts/collect_drive_letters.ini
lerc_control/scripts/collect_installed_drivers.ini
lerc_control/scripts/collect_local_admins.ini
lerc_control/scripts/collect_logon_sessions.ini
lerc_control/scripts/collect_logparser_prefetch.ini
lerc_control/scripts/collect_logparser_registry.ini
lerc_control/scripts/collect_logparser_sec_sys_app_event_logs.ini
lerc_control/scripts/collect_mapped_drives.ini
lerc_control/scripts/collect_memory.ini
lerc_control/scripts/collect_network_info.ini
lerc_control/scripts/collect_plug_play_devices.ini
lerc_control/scripts/collect_process_handles.ini
lerc_control/scripts/collect_pslist.ini
lerc_control/scripts/collect_scheduled_tasks.ini
lerc_control/scripts/collect_useraccounts.ini
lerc_control/scripts/collect_wmi_data.ini
lerc_control/scripts/collect_wmi_netuse.ini
lerc_control/scripts/collect_wmi_network_adapters.ini
lerc_control/scripts/collect_wmi_services.ini
lerc_control/scripts/collect_wmi_sliced.ini
lerc_control/scripts/collect_wmi_startup.ini
lerc_control/scripts/collect_wmi_timezone.ini
lerc_control/scripts/force_restart.ini
lerc_control/scripts/get_process_memory.ini
lerc_control/scripts/get_process_memstrings.ini
lerc_control/tools/7za.exe
lerc_control/tools/BrowsingHistoryView.exe
lerc_control/tools/InstalledDriversList.exe
lerc_control/tools/LogParser.dll
lerc_control/tools/autorunsc.exe
lerc_control/tools/deploy_lerc.ini
lerc_control-0.0.24.dist-info/LICENSE
lerc_control-0.0.24.dist-info/METADATA
lerc_control-0.0.24.dist-info/WHEEL
lerc_control-0.0.24.dist-info/top_level.txt
lerc_control-0.0.24.dist-info/RECORD
