Metadata-Version: 2.1
Name: lerc-control
Version: 0.0.24
Summary: Libraries and utilities for controling and working with Live Endpoint Response Clients.
Home-page: https://github.com/ace-ecosystem/lerc/lerc_control
Author: Sean McFeely
Author-email: mcfeelynaes@gmail.com
License: Apache-2.0
Keywords: Incident Response,Live Endpoint Response Client,LERC,Remote Administration Tool
Platform: UNKNOWN
Classifier: Development Status :: 4 - Beta
Classifier: Intended Audience :: Developers
Classifier: Intended Audience :: Information Technology
Classifier: Intended Audience :: Telecommunications Industry
Classifier: Operating System :: OS Independent
Classifier: License :: OSI Approved :: Apache Software License
Classifier: Programming Language :: Python :: 3 :: Only
Classifier: Programming Language :: Python :: 3
Classifier: Programming Language :: Python :: 3.0
Classifier: Programming Language :: Python :: 3.1
Classifier: Programming Language :: Python :: 3.2
Classifier: Programming Language :: Python :: 3.3
Classifier: Programming Language :: Python :: 3.4
Classifier: Programming Language :: Python :: 3.5
Classifier: Programming Language :: Python :: 3.6
Requires-Dist: coloredlogs
Requires-Dist: python-dateutil
Requires-Dist: requests
Requires-Dist: rotl (>=0.0.5)
Requires-Dist: tqdm
Requires-Dist: argcomplete
Requires-Dist: progressbar
